Metadata-Version: 2.1
Name: odoo11-addon-l10n-es-aeat-sii
Version: 11.0.2.8.0
Summary: Suministro Inmediato de Información en el IVA
Home-page: https://github.com/OCA/l10n-spain
Author: Acysos S.L.,Diagram,Minorisa,Studio73,FactorLibre,Comunitea,Otherway,Tecnativa,Javi Melendez,Odoo Community Association (OCA)
Author-email: support@odoo-community.org
License: AGPL-3
Platform: UNKNOWN
Classifier: Programming Language :: Python
Classifier: Framework :: Odoo
Classifier: Framework :: Odoo :: 11.0
Classifier: License :: OSI Approved :: GNU Affero General Public License v3
Classifier: Development Status :: 5 - Production/Stable
Requires-Python: >=2.7, !=3.0.*, !=3.1.*, !=3.2.*, !=3.3.*, !=3.4.*
Requires-Dist: odoo11-addon-account-invoice-refund-link
Requires-Dist: odoo11-addon-l10n-es-aeat
Requires-Dist: odoo11-addon-queue-job
Requires-Dist: odoo (<11.1dev,>=11.0a)
Requires-Dist: pyOpenSSL
Requires-Dist: requests
Requires-Dist: zeep
